purplship/mappers/dhl_express/__init__.py
purplship/mappers/dhl_express/mapper.py
purplship/mappers/dhl_express/proxy.py
purplship/mappers/dhl_express/settings.py
purplship/providers/dhl_express/__init__.py
purplship/providers/dhl_express/address.py
purplship/providers/dhl_express/error.py
purplship/providers/dhl_express/pickup/__init__.py
purplship/providers/dhl_express/pickup/cancel.py
purplship/providers/dhl_express/pickup/create.py
purplship/providers/dhl_express/pickup/update.py
purplship/providers/dhl_express/rate.py
purplship/providers/dhl_express/shipment.py
purplship/providers/dhl_express/tracking.py
purplship/providers/dhl_express/units.py
purplship/providers/dhl_express/utils.py
purplship.dhl_express-2022.2.dist-info/WHEEL
purplship.dhl_express-2022.2.dist-info/METADATA
purplship.dhl_express-2022.2.dist-info/RECORD
